better_qdrant_mcp/__init__.py
better_qdrant_mcp/__main__.py
better_qdrant_mcp/config.py
better_qdrant_mcp/embeddings.py
better_qdrant_mcp/py.typed
better_qdrant_mcp/qdr_client.py
better_qdrant_mcp/tools.py
better_qdrant_mcp/version.py
better_qdrant_mcp-0.3.1.dist-info/WHEEL
better_qdrant_mcp-0.3.1.dist-info/entry_points.txt
better_qdrant_mcp-0.3.1.dist-info/METADATA
better_qdrant_mcp-0.3.1.dist-info/RECORD
