Metadata-Version: 2.3
Name: better-qdrant-mcp
Version: 0.3.1
Summary: A Python MCP server for Qdrant memory storage and semantic search, compatible with Cursor-like MCP clients.
Keywords: mcp,model-context-protocol,qdrant,vector-database,semantic-search,memory
Author: jtsang4
Author-email: jtsang4 <info@jtsang.me>
Classifier: Programming Language :: Python :: 3
Classifier: Programming Language :: Python :: 3.12
Classifier: License :: OSI Approved :: MIT License
Classifier: Intended Audience :: Developers
Classifier: Topic :: Database
Classifier: Topic :: Scientific/Engineering :: Artificial Intelligence
Requires-Dist: fastembed>=0.7.3
Requires-Dist: fastmcp>=2.13.1
Requires-Dist: jieba>=0.42.1
Requires-Dist: openai>=1.47.0
Requires-Dist: qdrant-client>=1.15.1
Requires-Dist: uvicorn>=0.30.0
Requires-Dist: starlette>=0.40.0
Requires-Python: >=3.12
Project-URL: Documentation, https://github.com/jtsang4/better-qdrant-mcp#readme
Project-URL: Homepage, https://github.com/jtsang4/better-qdrant-mcp
Project-URL: Issues, https://github.com/jtsang4/better-qdrant-mcp/issues
Project-URL: Repository, https://github.com/jtsang4/better-qdrant-mcp
